<?xml version="1.0" encoding="utf-8"?>
<ArrayOfAssignment xmlns:xsi="http://www.w3.org/2001/XMLSchema-instance" xmlns:xsd="http://www.w3.org/2001/XMLSchema">
  <Assignment>
    <Id>0</Id>
    <CallId>2</CallId>
    <VolunteerId>282873264</VolunteerId>
    <EntryTime>2025-01-30T14:49:39</EntryTime>
    <CompletionTime>2025-01-30T15:20:39</CompletionTime>
    <CompletionStatus>Handled</CompletionStatus>
  </Assignment>
  <Assignment>
    <Id>2</Id>
    <CallId>6</CallId>
    <VolunteerId>224055293</VolunteerId>
    <EntryTime>2025-01-30T14:57:39</EntryTime>
    <CompletionTime>2025-01-30T15:00:39</CompletionTime>
    <CompletionStatus>Handled</CompletionStatus>
  </Assignment>
  <Assignment>
    <Id>3</Id>
    <CallId>8</CallId>
    <VolunteerId>320162951</VolunteerId>
    <EntryTime>2025-01-30T15:01:39</EntryTime>
    <CompletionTime>2025-01-30T15:14:39</CompletionTime>
    <CompletionStatus>Handled</CompletionStatus>
  </Assignment>
  <Assignment>
    <Id>10</Id>
    <CallId>19</CallId>
    <VolunteerId>280066259</VolunteerId>
    <EntryTime>2025-01-30T14:38:39</EntryTime>
    <CompletionTime>2025-01-30T14:50:39</CompletionTime>
    <CompletionStatus>Expired</CompletionStatus>
  </Assignment>
  <Assignment>
    <Id>11</Id>
    <CallId>26</CallId>
    <VolunteerId>388195505</VolunteerId>
    <EntryTime>2025-01-30T14:34:39</EntryTime>
    <CompletionTime>2025-01-30T14:53:39</CompletionTime>
    <CompletionStatus>Handled</CompletionStatus>
  </Assignment>
  <Assignment>
    <Id>17</Id>
    <CallId>33</CallId>
    <VolunteerId>330350323</VolunteerId>
    <EntryTime>2025-01-30T15:16:39</EntryTime>
    <CompletionTime>2025-01-30T16:14:39</CompletionTime>
    <CompletionStatus xsi:nil="true" />
  </Assignment>
  <Assignment>
    <Id>19</Id>
    <CallId>41</CallId>
    <VolunteerId>265292540</VolunteerId>
    <EntryTime>2025-01-30T14:41:39</EntryTime>
    <CompletionTime>2025-01-30T15:00:39</CompletionTime>
    <CompletionStatus>Expired</CompletionStatus>
  </Assignment>
  <Assignment>
    <Id>20</Id>
    <CallId>42</CallId>
    <VolunteerId>281132456</VolunteerId>
    <EntryTime>2025-01-30T15:21:39</EntryTime>
    <CompletionTime>2025-01-30T15:42:39</CompletionTime>
    <CompletionStatus xsi:nil="true" />
  </Assignment>
  <Assignment>
    <Id>21</Id>
    <CallId>43</CallId>
    <VolunteerId>232312132</VolunteerId>
    <EntryTime>2025-01-30T14:54:39</EntryTime>
    <CompletionTime>2025-01-30T14:16:39</CompletionTime>
    <CompletionStatus>Expired</CompletionStatus>
  </Assignment>
  <Assignment>
    <Id>24</Id>
    <CallId>54</CallId>
    <VolunteerId>281132456</VolunteerId>
    <EntryTime>2025-01-30T15:14:39</EntryTime>
    <CompletionTime>2025-01-30T15:15:39</CompletionTime>
    <CompletionStatus xsi:nil="true" />
  </Assignment>
  <Assignment>
    <Id>25</Id>
    <CallId>55</CallId>
    <VolunteerId>281132456</VolunteerId>
    <EntryTime>2025-01-30T15:12:39</EntryTime>
    <CompletionTime>2025-01-30T15:51:39</CompletionTime>
    <CompletionStatus xsi:nil="true" />
  </Assignment>
  <Assignment>
    <Id>16</Id>
    <CallId>32</CallId>
    <VolunteerId>203762463</VolunteerId>
    <EntryTime>2025-01-30T15:17:39</EntryTime>
    <CompletionTime>2025-01-30T15:33:39</CompletionTime>
    <CompletionStatus>Handled</CompletionStatus>
  </Assignment>
  <Assignment>
    <Id>5</Id>
    <CallId>10</CallId>
    <VolunteerId>371987611</VolunteerId>
    <EntryTime>2025-01-30T14:53:39</EntryTime>
    <CompletionTime>2025-01-30T15:33:39</CompletionTime>
    <CompletionStatus>Handled</CompletionStatus>
  </Assignment>
  <Assignment>
    <Id>26</Id>
    <CallId>57</CallId>
    <VolunteerId>282520675</VolunteerId>
    <EntryTime>2025-01-30T15:20:39</EntryTime>
    <CompletionTime>2025-01-30T15:33:39</CompletionTime>
    <CompletionStatus>Handled</CompletionStatus>
  </Assignment>
  <Assignment>
    <Id>8</Id>
    <CallId>17</CallId>
    <VolunteerId>280066259</VolunteerId>
    <EntryTime>2025-01-30T15:02:39</EntryTime>
    <CompletionTime>2025-01-30T15:33:39</CompletionTime>
    <CompletionStatus>Handled</CompletionStatus>
  </Assignment>
  <Assignment>
    <Id>7</Id>
    <CallId>12</CallId>
    <VolunteerId>282873264</VolunteerId>
    <EntryTime>2025-01-30T15:17:39</EntryTime>
    <CompletionTime>2025-01-30T15:33:39</CompletionTime>
    <CompletionStatus>Handled</CompletionStatus>
  </Assignment>
  <Assignment>
    <Id>14</Id>
    <CallId>29</CallId>
    <VolunteerId>330350323</VolunteerId>
    <EntryTime>2025-01-30T15:11:39</EntryTime>
    <CompletionTime>2025-01-30T15:33:39</CompletionTime>
    <CompletionStatus>Handled</CompletionStatus>
  </Assignment>
  <Assignment>
    <Id>12</Id>
    <CallId>27</CallId>
    <VolunteerId>320162951</VolunteerId>
    <EntryTime>2025-01-30T15:14:39</EntryTime>
    <CompletionTime>2025-01-30T15:33:39</CompletionTime>
    <CompletionStatus>Handled</CompletionStatus>
  </Assignment>
  <Assignment>
    <Id>6</Id>
    <CallId>11</CallId>
    <VolunteerId>281132456</VolunteerId>
    <EntryTime>2025-01-30T14:58:39</EntryTime>
    <CompletionTime>2025-01-30T15:33:39</CompletionTime>
    <CompletionStatus>Handled</CompletionStatus>
  </Assignment>
  <Assignment>
    <Id>4</Id>
    <CallId>9</CallId>
    <VolunteerId>265292540</VolunteerId>
    <EntryTime>2025-01-30T14:51:39</EntryTime>
    <CompletionTime>2025-01-30T15:33:39</CompletionTime>
    <CompletionStatus>Handled</CompletionStatus>
  </Assignment>
  <Assignment>
    <Id>27</Id>
    <CallId>58</CallId>
    <VolunteerId>339054173</VolunteerId>
    <EntryTime>2025-01-30T15:21:39</EntryTime>
    <CompletionTime>2025-01-30T15:33:39</CompletionTime>
    <CompletionStatus>Handled</CompletionStatus>
  </Assignment>
  <Assignment>
    <Id>13</Id>
    <CallId>28</CallId>
    <VolunteerId>231550229</VolunteerId>
    <EntryTime>2025-01-30T14:40:39</EntryTime>
    <CompletionTime>2025-01-30T15:33:39</CompletionTime>
    <CompletionStatus>Handled</CompletionStatus>
  </Assignment>
  <Assignment>
    <Id>23</Id>
    <CallId>53</CallId>
    <VolunteerId>371987611</VolunteerId>
    <EntryTime>2025-01-30T15:12:39</EntryTime>
    <CompletionTime>2025-01-30T15:43:39</CompletionTime>
    <CompletionStatus>Handled</CompletionStatus>
  </Assignment>
  <Assignment>
    <Id>29</Id>
    <CallId>14</CallId>
    <VolunteerId>224055293</VolunteerId>
    <EntryTime>2025-01-30T15:43:39</EntryTime>
    <CompletionTime>2025-01-30T16:13:39</CompletionTime>
    <CompletionStatus>Handled</CompletionStatus>
  </Assignment>
  <Assignment>
    <Id>31</Id>
    <CallId>22</CallId>
    <VolunteerId>282520675</VolunteerId>
    <EntryTime>2025-01-30T16:13:39</EntryTime>
    <CompletionTime>2025-01-30T16:14:39</CompletionTime>
    <CompletionStatus>Handled</CompletionStatus>
  </Assignment>
  <Assignment>
    <Id>30</Id>
    <CallId>58</CallId>
    <VolunteerId>320162951</VolunteerId>
    <EntryTime>2025-01-30T15:43:39</EntryTime>
    <CompletionTime>2025-01-30T16:14:39</CompletionTime>
    <CompletionStatus>Handled</CompletionStatus>
  </Assignment>
  <Assignment>
    <Id>9</Id>
    <CallId>18</CallId>
    <VolunteerId>265292540</VolunteerId>
    <EntryTime>2025-01-30T15:17:39</EntryTime>
    <CompletionTime>2025-01-30T16:14:39</CompletionTime>
    <CompletionStatus>Handled</CompletionStatus>
  </Assignment>
  <Assignment>
    <Id>22</Id>
    <CallId>44</CallId>
    <VolunteerId>388195505</VolunteerId>
    <EntryTime>2025-01-30T15:05:39</EntryTime>
    <CompletionTime>2025-01-30T16:14:39</CompletionTime>
    <CompletionStatus>Handled</CompletionStatus>
  </Assignment>
  <Assignment>
    <Id>28</Id>
    <CallId>59</CallId>
    <VolunteerId>231550229</VolunteerId>
    <EntryTime>2025-01-30T15:21:39</EntryTime>
    <CompletionTime>2025-01-30T16:14:39</CompletionTime>
    <CompletionStatus>Handled</CompletionStatus>
  </Assignment>
  <Assignment>
    <Id>32</Id>
    <CallId>7</CallId>
    <VolunteerId>203762463</VolunteerId>
    <EntryTime>2025-01-30T16:14:39</EntryTime>
    <CompletionTime>2025-01-30T16:15:39</CompletionTime>
    <CompletionStatus>Handled</CompletionStatus>
  </Assignment>
  <Assignment>
    <Id>34</Id>
    <CallId>0</CallId>
    <VolunteerId>371987611</VolunteerId>
    <EntryTime>2025-01-30T16:15:39</EntryTime>
    <CompletionTime>2025-01-30T16:16:39</CompletionTime>
    <CompletionStatus>Handled</CompletionStatus>
  </Assignment>
  <Assignment>
    <Id>35</Id>
    <CallId>53</CallId>
    <VolunteerId>282520675</VolunteerId>
    <EntryTime>2025-01-30T16:15:39</EntryTime>
    <CompletionTime>2025-01-30T16:16:39</CompletionTime>
    <CompletionStatus>Handled</CompletionStatus>
  </Assignment>
  <Assignment>
    <Id>18</Id>
    <CallId>34</CallId>
    <VolunteerId>265292540</VolunteerId>
    <EntryTime>2025-01-30T15:10:39</EntryTime>
    <CompletionTime>2025-01-30T16:16:39</CompletionTime>
    <CompletionStatus>Handled</CompletionStatus>
  </Assignment>
  <Assignment>
    <Id>36</Id>
    <CallId>40</CallId>
    <VolunteerId>224055293</VolunteerId>
    <EntryTime>2025-01-30T16:16:39</EntryTime>
    <CompletionTime>2025-01-30T16:17:39</CompletionTime>
    <CompletionStatus>Handled</CompletionStatus>
  </Assignment>
  <Assignment>
    <Id>39</Id>
    <CallId>40</CallId>
    <VolunteerId>320162951</VolunteerId>
    <EntryTime>2025-01-30T16:17:39</EntryTime>
    <CompletionTime>2025-01-30T16:18:39</CompletionTime>
    <CompletionStatus>Handled</CompletionStatus>
  </Assignment>
  <Assignment>
    <Id>40</Id>
    <CallId>50</CallId>
    <VolunteerId>265292540</VolunteerId>
    <EntryTime>2025-01-30T16:17:39</EntryTime>
    <CompletionTime>2025-01-30T16:18:39</CompletionTime>
    <CompletionStatus>Handled</CompletionStatus>
  </Assignment>
  <Assignment>
    <Id>41</Id>
    <CallId>15</CallId>
    <VolunteerId>339054173</VolunteerId>
    <EntryTime>2025-01-30T16:17:39</EntryTime>
    <CompletionTime>2025-01-30T16:18:39</CompletionTime>
    <CompletionStatus>Handled</CompletionStatus>
  </Assignment>
  <Assignment>
    <Id>43</Id>
    <CallId>60</CallId>
    <VolunteerId>203762463</VolunteerId>
    <EntryTime>2025-01-30T16:18:39</EntryTime>
    <CompletionTime>2025-01-30T16:19:39</CompletionTime>
    <CompletionStatus>Handled</CompletionStatus>
  </Assignment>
  <Assignment>
    <Id>45</Id>
    <CallId>1</CallId>
    <VolunteerId>280066259</VolunteerId>
    <EntryTime>2025-01-30T16:18:39</EntryTime>
    <CompletionTime>2025-01-30T16:19:39</CompletionTime>
    <CompletionStatus>Handled</CompletionStatus>
  </Assignment>
  <Assignment>
    <Id>46</Id>
    <CallId>27</CallId>
    <VolunteerId>320162951</VolunteerId>
    <EntryTime>2025-01-30T16:19:39</EntryTime>
    <CompletionTime>2025-01-30T16:20:39</CompletionTime>
    <CompletionStatus>Handled</CompletionStatus>
  </Assignment>
  <Assignment>
    <Id>47</Id>
    <CallId>27</CallId>
    <VolunteerId>202973020</VolunteerId>
    <EntryTime>2025-01-30T16:19:39</EntryTime>
    <CompletionTime>2025-01-30T16:20:39</CompletionTime>
    <CompletionStatus>Handled</CompletionStatus>
  </Assignment>
  <Assignment>
    <Id>48</Id>
    <CallId>17</CallId>
    <VolunteerId>203762463</VolunteerId>
    <EntryTime>2025-01-30T16:20:39</EntryTime>
    <CompletionTime>2025-01-30T16:21:39</CompletionTime>
    <CompletionStatus>Handled</CompletionStatus>
  </Assignment>
  <Assignment>
    <Id>49</Id>
    <CallId>1</CallId>
    <VolunteerId>280066259</VolunteerId>
    <EntryTime>2025-01-30T16:20:39</EntryTime>
    <CompletionTime>2025-01-30T16:21:39</CompletionTime>
    <CompletionStatus>Handled</CompletionStatus>
  </Assignment>
  <Assignment>
    <Id>50</Id>
    <CallId>7</CallId>
    <VolunteerId>282873264</VolunteerId>
    <EntryTime>2025-01-30T16:20:39</EntryTime>
    <CompletionTime>2025-01-30T16:21:39</CompletionTime>
    <CompletionStatus>Handled</CompletionStatus>
  </Assignment>
  <Assignment>
    <Id>51</Id>
    <CallId>10</CallId>
    <VolunteerId>388195505</VolunteerId>
    <EntryTime>2025-01-30T16:20:39</EntryTime>
    <CompletionTime>2025-01-30T16:21:39</CompletionTime>
    <CompletionStatus>Handled</CompletionStatus>
  </Assignment>
  <Assignment>
    <Id>53</Id>
    <CallId>4</CallId>
    <VolunteerId>371987611</VolunteerId>
    <EntryTime>2025-01-30T16:21:39</EntryTime>
    <CompletionTime>2025-01-30T16:22:39</CompletionTime>
    <CompletionStatus>Handled</CompletionStatus>
  </Assignment>
  <Assignment>
    <Id>55</Id>
    <CallId>20</CallId>
    <VolunteerId>282520675</VolunteerId>
    <EntryTime>2025-01-30T16:22:39</EntryTime>
    <CompletionTime>2025-01-30T16:23:39</CompletionTime>
    <CompletionStatus>Handled</CompletionStatus>
  </Assignment>
  <Assignment>
    <Id>56</Id>
    <CallId>52</CallId>
    <VolunteerId>339054173</VolunteerId>
    <EntryTime>2025-01-30T16:22:39</EntryTime>
    <CompletionTime>2025-01-30T16:23:39</CompletionTime>
    <CompletionStatus>Handled</CompletionStatus>
  </Assignment>
  <Assignment>
    <Id>57</Id>
    <CallId>51</CallId>
    <VolunteerId>280066259</VolunteerId>
    <EntryTime>2025-01-30T16:23:39</EntryTime>
    <CompletionTime>2025-01-30T16:33:39</CompletionTime>
    <CompletionStatus>Handled</CompletionStatus>
  </Assignment>
  <Assignment>
    <Id>58</Id>
    <CallId>44</CallId>
    <VolunteerId>282873264</VolunteerId>
    <EntryTime>2025-01-30T16:23:39</EntryTime>
    <CompletionTime>2025-01-30T16:33:39</CompletionTime>
    <CompletionStatus>Handled</CompletionStatus>
  </Assignment>
  <Assignment>
    <Id>59</Id>
    <CallId>25</CallId>
    <VolunteerId>231550229</VolunteerId>
    <EntryTime>2025-01-30T16:23:39</EntryTime>
    <CompletionTime>2025-01-30T16:33:39</CompletionTime>
    <CompletionStatus>Handled</CompletionStatus>
  </Assignment>
  <Assignment>
    <Id>60</Id>
    <CallId>31</CallId>
    <VolunteerId>339054173</VolunteerId>
    <EntryTime>2025-01-30T16:33:39</EntryTime>
    <CompletionTime>2025-01-30T16:43:39</CompletionTime>
    <CompletionStatus>Handled</CompletionStatus>
  </Assignment>
  <Assignment>
    <Id>61</Id>
    <CallId>40</CallId>
    <VolunteerId>320162951</VolunteerId>
    <EntryTime>2025-01-30T16:43:39</EntryTime>
    <CompletionTime>2025-01-30T16:53:39</CompletionTime>
    <CompletionStatus>Handled</CompletionStatus>
  </Assignment>
  <Assignment>
    <Id>62</Id>
    <CallId>33</CallId>
    <VolunteerId>388195505</VolunteerId>
    <EntryTime>2025-01-30T16:43:39</EntryTime>
    <CompletionTime>2025-01-30T16:53:39</CompletionTime>
    <CompletionStatus>Handled</CompletionStatus>
  </Assignment>
  <Assignment>
    <Id>63</Id>
    <CallId>15</CallId>
    <VolunteerId>202973020</VolunteerId>
    <EntryTime>2025-01-30T16:43:39</EntryTime>
    <CompletionTime>2025-01-30T16:53:39</CompletionTime>
    <CompletionStatus>Handled</CompletionStatus>
  </Assignment>
  <Assignment>
    <Id>64</Id>
    <CallId>22</CallId>
    <VolunteerId>282520675</VolunteerId>
    <EntryTime>2025-01-30T16:53:39</EntryTime>
    <CompletionTime>2025-01-30T17:03:39</CompletionTime>
    <CompletionStatus>Handled</CompletionStatus>
  </Assignment>
  <Assignment>
    <Id>65</Id>
    <CallId>51</CallId>
    <VolunteerId>280066259</VolunteerId>
    <EntryTime>2025-01-30T16:53:39</EntryTime>
    <CompletionTime>2025-01-30T17:03:39</CompletionTime>
    <CompletionStatus>Handled</CompletionStatus>
  </Assignment>
  <Assignment>
    <Id>66</Id>
    <CallId>39</CallId>
    <VolunteerId>265292540</VolunteerId>
    <EntryTime>2025-01-30T16:53:39</EntryTime>
    <CompletionTime>2025-01-30T17:03:39</CompletionTime>
    <CompletionStatus>Handled</CompletionStatus>
  </Assignment>
  <Assignment>
    <Id>67</Id>
    <CallId>16</CallId>
    <VolunteerId>231550229</VolunteerId>
    <EntryTime>2025-01-30T16:53:39</EntryTime>
    <CompletionTime>2025-01-30T17:03:39</CompletionTime>
    <CompletionStatus>Handled</CompletionStatus>
  </Assignment>
  <Assignment>
    <Id>68</Id>
    <CallId>16</CallId>
    <VolunteerId>328308721</VolunteerId>
    <EntryTime>2025-01-30T16:53:39</EntryTime>
    <CompletionTime>2025-01-30T17:03:39</CompletionTime>
    <CompletionStatus>Handled</CompletionStatus>
  </Assignment>
  <Assignment>
    <Id>69</Id>
    <CallId>61</CallId>
    <VolunteerId>371987611</VolunteerId>
    <EntryTime>2025-01-30T17:03:39</EntryTime>
    <CompletionTime>2025-01-30T17:13:39</CompletionTime>
    <CompletionStatus>Handled</CompletionStatus>
  </Assignment>
  <Assignment>
    <Id>70</Id>
    <CallId>38</CallId>
    <VolunteerId>320162951</VolunteerId>
    <EntryTime>2025-01-30T17:03:39</EntryTime>
    <CompletionTime>2025-01-30T17:13:39</CompletionTime>
    <CompletionStatus>Handled</CompletionStatus>
  </Assignment>
  <Assignment>
    <Id>71</Id>
    <CallId>42</CallId>
    <VolunteerId>339054173</VolunteerId>
    <EntryTime>2025-01-30T17:03:39</EntryTime>
    <CompletionTime>2025-01-30T17:13:39</CompletionTime>
    <CompletionStatus>Handled</CompletionStatus>
  </Assignment>
  <Assignment>
    <Id>72</Id>
    <CallId>1</CallId>
    <VolunteerId>280066259</VolunteerId>
    <EntryTime>2025-01-30T17:13:39</EntryTime>
    <CompletionTime>2025-01-30T17:23:39</CompletionTime>
    <CompletionStatus>Handled</CompletionStatus>
  </Assignment>
  <Assignment>
    <Id>73</Id>
    <CallId>25</CallId>
    <VolunteerId>231550229</VolunteerId>
    <EntryTime>2025-01-30T17:13:39</EntryTime>
    <CompletionTime>2025-01-30T17:23:39</CompletionTime>
    <CompletionStatus>Handled</CompletionStatus>
  </Assignment>
  <Assignment>
    <Id>74</Id>
    <CallId>60</CallId>
    <VolunteerId>265292540</VolunteerId>
    <EntryTime>2025-01-30T17:23:39</EntryTime>
    <CompletionTime>2025-01-30T17:33:39</CompletionTime>
    <CompletionStatus>Handled</CompletionStatus>
  </Assignment>
  <Assignment>
    <Id>75</Id>
    <CallId>18</CallId>
    <VolunteerId>232312132</VolunteerId>
    <EntryTime>2025-01-30T17:23:39</EntryTime>
    <CompletionTime>2025-01-30T17:33:39</CompletionTime>
    <CompletionStatus>Handled</CompletionStatus>
  </Assignment>
  <Assignment>
    <Id>76</Id>
    <CallId>37</CallId>
    <VolunteerId>203762463</VolunteerId>
    <EntryTime>2025-01-30T17:33:39</EntryTime>
    <CompletionTime>2025-01-30T17:43:39</CompletionTime>
    <CompletionStatus>Handled</CompletionStatus>
  </Assignment>
  <Assignment>
    <Id>77</Id>
    <CallId>16</CallId>
    <VolunteerId>224055293</VolunteerId>
    <EntryTime>2025-01-30T17:33:39</EntryTime>
    <CompletionTime>2025-01-30T17:43:39</CompletionTime>
    <CompletionStatus>Handled</CompletionStatus>
  </Assignment>
  <Assignment>
    <Id>78</Id>
    <CallId>1</CallId>
    <VolunteerId>280066259</VolunteerId>
    <EntryTime>2025-01-30T17:33:39</EntryTime>
    <CompletionTime>2025-01-30T17:43:39</CompletionTime>
    <CompletionStatus>Handled</CompletionStatus>
  </Assignment>
  <Assignment>
    <Id>79</Id>
    <CallId>36</CallId>
    <VolunteerId>371987611</VolunteerId>
    <EntryTime>2025-01-30T17:43:39</EntryTime>
    <CompletionTime>2025-01-30T17:53:39</CompletionTime>
    <CompletionStatus>Handled</CompletionStatus>
  </Assignment>
  <Assignment>
    <Id>80</Id>
    <CallId>17</CallId>
    <VolunteerId>282520675</VolunteerId>
    <EntryTime>2025-01-30T17:43:39</EntryTime>
    <CompletionTime>2025-01-30T17:53:39</CompletionTime>
    <CompletionStatus>Handled</CompletionStatus>
  </Assignment>
  <Assignment>
    <Id>81</Id>
    <CallId>25</CallId>
    <VolunteerId>388195505</VolunteerId>
    <EntryTime>2025-01-30T17:43:39</EntryTime>
    <CompletionTime>2025-01-30T17:53:39</CompletionTime>
    <CompletionStatus>Handled</CompletionStatus>
  </Assignment>
  <Assignment>
    <Id>82</Id>
    <CallId>38</CallId>
    <VolunteerId>231550229</VolunteerId>
    <EntryTime>2025-01-30T17:43:39</EntryTime>
    <CompletionTime>2025-01-30T17:53:39</CompletionTime>
    <CompletionStatus>Handled</CompletionStatus>
  </Assignment>
  <Assignment>
    <Id>83</Id>
    <CallId>53</CallId>
    <VolunteerId>265292540</VolunteerId>
    <EntryTime>2025-01-30T17:53:39</EntryTime>
    <CompletionTime>2025-01-30T18:03:39</CompletionTime>
    <CompletionStatus>Handled</CompletionStatus>
  </Assignment>
  <Assignment>
    <Id>85</Id>
    <CallId>38</CallId>
    <VolunteerId>328308721</VolunteerId>
    <EntryTime>2025-01-30T18:03:39</EntryTime>
    <CompletionTime>2025-01-30T18:13:39</CompletionTime>
    <CompletionStatus>Handled</CompletionStatus>
  </Assignment>
  <Assignment>
    <Id>84</Id>
    <CallId>51</CallId>
    <VolunteerId>280066259</VolunteerId>
    <EntryTime>2025-01-30T18:03:39</EntryTime>
    <CompletionTime>2025-01-30T18:23:39</CompletionTime>
    <CompletionStatus>Handled</CompletionStatus>
  </Assignment>
  <Assignment>
    <Id>86</Id>
    <CallId>55</CallId>
    <VolunteerId>282873264</VolunteerId>
    <EntryTime>2025-01-30T18:13:39</EntryTime>
    <CompletionTime>2025-01-30T18:23:39</CompletionTime>
    <CompletionStatus>Handled</CompletionStatus>
  </Assignment>
  <Assignment>
    <Id>87</Id>
    <CallId>16</CallId>
    <VolunteerId>320162951</VolunteerId>
    <EntryTime>2025-01-30T18:13:39</EntryTime>
    <CompletionTime>2025-01-30T18:23:39</CompletionTime>
    <CompletionStatus>Handled</CompletionStatus>
  </Assignment>
  <Assignment>
    <Id>88</Id>
    <CallId>52</CallId>
    <VolunteerId>388195505</VolunteerId>
    <EntryTime>2025-01-30T18:13:39</EntryTime>
    <CompletionTime>2025-01-30T18:23:39</CompletionTime>
    <CompletionStatus>Handled</CompletionStatus>
  </Assignment>
  <Assignment>
    <Id>89</Id>
    <CallId>10</CallId>
    <VolunteerId>339054173</VolunteerId>
    <EntryTime>2025-01-30T18:13:39</EntryTime>
    <CompletionTime>2025-01-30T18:23:39</CompletionTime>
    <CompletionStatus>Handled</CompletionStatus>
  </Assignment>
  <Assignment>
    <Id>90</Id>
    <CallId>18</CallId>
    <VolunteerId>232312132</VolunteerId>
    <EntryTime>2025-01-30T18:13:39</EntryTime>
    <CompletionTime>2025-01-30T18:23:39</CompletionTime>
    <CompletionStatus>Handled</CompletionStatus>
  </Assignment>
  <Assignment>
    <Id>91</Id>
    <CallId>29</CallId>
    <VolunteerId>371987611</VolunteerId>
    <EntryTime>2025-01-30T18:23:39</EntryTime>
    <CompletionTime>2025-01-30T18:33:39</CompletionTime>
    <CompletionStatus>Handled</CompletionStatus>
  </Assignment>
  <Assignment>
    <Id>92</Id>
    <CallId>16</CallId>
    <VolunteerId>328308721</VolunteerId>
    <EntryTime>2025-01-30T18:23:39</EntryTime>
    <CompletionTime>2025-01-30T18:33:39</CompletionTime>
    <CompletionStatus>Handled</CompletionStatus>
  </Assignment>
  <Assignment>
    <Id>93</Id>
    <CallId>36</CallId>
    <VolunteerId>282520675</VolunteerId>
    <EntryTime>2025-01-30T18:33:39</EntryTime>
    <CompletionTime>2025-01-30T18:43:39</CompletionTime>
    <CompletionStatus>Handled</CompletionStatus>
  </Assignment>
  <Assignment>
    <Id>94</Id>
    <CallId>22</CallId>
    <VolunteerId>265292540</VolunteerId>
    <EntryTime>2025-01-30T18:33:39</EntryTime>
    <CompletionTime>2025-01-30T18:43:39</CompletionTime>
    <CompletionStatus>Handled</CompletionStatus>
  </Assignment>
  <Assignment>
    <Id>95</Id>
    <CallId>24</CallId>
    <VolunteerId>202973020</VolunteerId>
    <EntryTime>2025-01-30T18:33:39</EntryTime>
    <CompletionTime>2025-01-30T18:43:39</CompletionTime>
    <CompletionStatus>Handled</CompletionStatus>
  </Assignment>
  <Assignment>
    <Id>96</Id>
    <CallId>52</CallId>
    <VolunteerId>339054173</VolunteerId>
    <EntryTime>2025-01-30T18:33:39</EntryTime>
    <CompletionTime>2025-01-30T18:43:39</CompletionTime>
    <CompletionStatus>Handled</CompletionStatus>
  </Assignment>
  <Assignment>
    <Id>97</Id>
    <CallId>59</CallId>
    <VolunteerId>231550229</VolunteerId>
    <EntryTime>2025-01-30T18:33:39</EntryTime>
    <CompletionTime>2025-01-30T18:43:39</CompletionTime>
    <CompletionStatus>Handled</CompletionStatus>
  </Assignment>
  <Assignment>
    <Id>98</Id>
    <CallId>57</CallId>
    <VolunteerId>282873264</VolunteerId>
    <EntryTime>2025-01-30T18:43:39</EntryTime>
    <CompletionTime>2025-01-30T18:53:39</CompletionTime>
    <CompletionStatus>Handled</CompletionStatus>
  </Assignment>
  <Assignment>
    <Id>99</Id>
    <CallId>56</CallId>
    <VolunteerId>320162951</VolunteerId>
    <EntryTime>2025-01-30T18:43:39</EntryTime>
    <CompletionTime>2025-01-30T18:53:39</CompletionTime>
    <CompletionStatus>Handled</CompletionStatus>
  </Assignment>
  <Assignment>
    <Id>100</Id>
    <CallId>18</CallId>
    <VolunteerId>232312132</VolunteerId>
    <EntryTime>2025-01-30T18:43:39</EntryTime>
    <CompletionTime>2025-01-30T18:53:39</CompletionTime>
    <CompletionStatus>Handled</CompletionStatus>
  </Assignment>
  <Assignment>
    <Id>101</Id>
    <CallId>39</CallId>
    <VolunteerId>265292540</VolunteerId>
    <EntryTime>2025-01-30T18:53:39</EntryTime>
    <CompletionTime>2025-01-30T19:03:39</CompletionTime>
    <CompletionStatus>Handled</CompletionStatus>
  </Assignment>
  <Assignment>
    <Id>102</Id>
    <CallId>53</CallId>
    <VolunteerId>388195505</VolunteerId>
    <EntryTime>2025-01-30T19:03:39</EntryTime>
    <CompletionTime>2025-01-30T19:13:39</CompletionTime>
    <CompletionStatus>Handled</CompletionStatus>
  </Assignment>
  <Assignment>
    <Id>103</Id>
    <CallId>18</CallId>
    <VolunteerId>232312132</VolunteerId>
    <EntryTime>2025-01-30T19:03:39</EntryTime>
    <CompletionTime>2025-01-30T19:13:39</CompletionTime>
    <CompletionStatus>Handled</CompletionStatus>
  </Assignment>
  <Assignment>
    <Id>104</Id>
    <CallId>9</CallId>
    <VolunteerId>328308721</VolunteerId>
    <EntryTime>2025-01-30T19:03:39</EntryTime>
    <CompletionTime>2025-01-30T19:13:39</CompletionTime>
    <CompletionStatus>Handled</CompletionStatus>
  </Assignment>
  <Assignment>
    <Id>105</Id>
    <CallId>54</CallId>
    <VolunteerId>371987611</VolunteerId>
    <EntryTime>2025-01-30T19:13:39</EntryTime>
    <CompletionTime>2025-01-30T19:23:39</CompletionTime>
    <CompletionStatus>Handled</CompletionStatus>
  </Assignment>
  <Assignment>
    <Id>106</Id>
    <CallId>32</CallId>
    <VolunteerId>224055293</VolunteerId>
    <EntryTime>2025-01-30T19:13:39</EntryTime>
    <CompletionTime>2025-01-30T19:23:39</CompletionTime>
    <CompletionStatus>Handled</CompletionStatus>
  </Assignment>
  <Assignment>
    <Id>107</Id>
    <CallId>1</CallId>
    <VolunteerId>280066259</VolunteerId>
    <EntryTime>2025-01-30T19:13:39</EntryTime>
    <CompletionTime>2025-01-30T19:23:39</CompletionTime>
    <CompletionStatus>Handled</CompletionStatus>
  </Assignment>
  <Assignment>
    <Id>108</Id>
    <CallId>39</CallId>
    <VolunteerId>203762463</VolunteerId>
    <EntryTime>2025-01-30T19:23:39</EntryTime>
    <CompletionTime>2025-01-30T19:33:39</CompletionTime>
    <CompletionStatus>Handled</CompletionStatus>
  </Assignment>
  <Assignment>
    <Id>109</Id>
    <CallId>51</CallId>
    <VolunteerId>280066259</VolunteerId>
    <EntryTime>2025-01-30T19:33:39</EntryTime>
    <CompletionTime>2025-01-30T19:43:39</CompletionTime>
    <CompletionStatus>Handled</CompletionStatus>
  </Assignment>
  <Assignment>
    <Id>110</Id>
    <CallId>15</CallId>
    <VolunteerId>265292540</VolunteerId>
    <EntryTime>2025-01-30T19:33:39</EntryTime>
    <CompletionTime>2025-01-30T19:43:39</CompletionTime>
    <CompletionStatus>Handled</CompletionStatus>
  </Assignment>
  <Assignment>
    <Id>111</Id>
    <CallId>31</CallId>
    <VolunteerId>202973020</VolunteerId>
    <EntryTime>2025-01-30T19:33:39</EntryTime>
    <CompletionTime>2025-01-30T19:43:39</CompletionTime>
    <CompletionStatus>Handled</CompletionStatus>
  </Assignment>
  <Assignment>
    <Id>112</Id>
    <CallId>59</CallId>
    <VolunteerId>224055293</VolunteerId>
    <EntryTime>2025-01-30T19:53:39</EntryTime>
    <CompletionTime>2025-01-30T20:03:39</CompletionTime>
    <CompletionStatus>Handled</CompletionStatus>
  </Assignment>
  <Assignment>
    <Id>113</Id>
    <CallId>44</CallId>
    <VolunteerId>388195505</VolunteerId>
    <EntryTime>2025-01-30T19:53:39</EntryTime>
    <CompletionTime>2025-01-30T20:03:39</CompletionTime>
    <CompletionStatus>Handled</CompletionStatus>
  </Assignment>
  <Assignment>
    <Id>115</Id>
    <CallId>25</CallId>
    <VolunteerId>231550229</VolunteerId>
    <EntryTime>2025-01-30T19:53:39</EntryTime>
    <CompletionTime>2025-01-30T20:03:39</CompletionTime>
    <CompletionStatus>Handled</CompletionStatus>
  </Assignment>
  <Assignment>
    <Id>116</Id>
    <CallId>44</CallId>
    <VolunteerId>202973020</VolunteerId>
    <EntryTime>2025-01-30T20:03:39</EntryTime>
    <CompletionTime>2025-01-30T20:13:39</CompletionTime>
    <CompletionStatus>Handled</CompletionStatus>
  </Assignment>
  <Assignment>
    <Id>114</Id>
    <CallId>18</CallId>
    <VolunteerId>232312132</VolunteerId>
    <EntryTime>2025-01-30T19:53:39</EntryTime>
    <CompletionTime>2025-01-30T20:13:39</CompletionTime>
    <CompletionStatus>Handled</CompletionStatus>
  </Assignment>
  <Assignment>
    <Id>117</Id>
    <CallId>52</CallId>
    <VolunteerId>282873264</VolunteerId>
    <EntryTime>2025-01-30T20:13:39</EntryTime>
    <CompletionTime>2025-01-30T20:23:39</CompletionTime>
    <CompletionStatus>Handled</CompletionStatus>
  </Assignment>
  <Assignment>
    <Id>118</Id>
    <CallId>29</CallId>
    <VolunteerId>388195505</VolunteerId>
    <EntryTime>2025-01-30T20:13:39</EntryTime>
    <CompletionTime>2025-01-30T20:23:39</CompletionTime>
    <CompletionStatus>Handled</CompletionStatus>
  </Assignment>
  <Assignment>
    <Id>119</Id>
    <CallId>58</CallId>
    <VolunteerId>320162951</VolunteerId>
    <EntryTime>2025-01-30T20:23:39</EntryTime>
    <CompletionTime>2025-01-30T20:33:39</CompletionTime>
    <CompletionStatus>Handled</CompletionStatus>
  </Assignment>
  <Assignment>
    <Id>120</Id>
    <CallId>25</CallId>
    <VolunteerId>202973020</VolunteerId>
    <EntryTime>2025-01-30T20:23:39</EntryTime>
    <CompletionTime>2025-01-30T20:33:39</CompletionTime>
    <CompletionStatus>Handled</CompletionStatus>
  </Assignment>
  <Assignment>
    <Id>121</Id>
    <CallId>33</CallId>
    <VolunteerId>339054173</VolunteerId>
    <EntryTime>2025-01-30T20:23:39</EntryTime>
    <CompletionTime>2025-01-30T20:33:39</CompletionTime>
    <CompletionStatus>Handled</CompletionStatus>
  </Assignment>
  <Assignment>
    <Id>122</Id>
    <CallId>54</CallId>
    <VolunteerId>371987611</VolunteerId>
    <EntryTime>2025-01-30T20:33:39</EntryTime>
    <CompletionTime>2025-01-30T20:43:39</CompletionTime>
    <CompletionStatus>Handled</CompletionStatus>
  </Assignment>
  <Assignment>
    <Id>123</Id>
    <CallId>58</CallId>
    <VolunteerId>388195505</VolunteerId>
    <EntryTime>2025-01-30T20:43:39</EntryTime>
    <CompletionTime>2025-01-30T20:53:39</CompletionTime>
    <CompletionStatus>Handled</CompletionStatus>
  </Assignment>
  <Assignment>
    <Id>124</Id>
    <CallId>31</CallId>
    <VolunteerId>339054173</VolunteerId>
    <EntryTime>2025-01-30T20:43:39</EntryTime>
    <CompletionTime>2025-01-30T20:53:39</CompletionTime>
    <CompletionStatus>Handled</CompletionStatus>
  </Assignment>
  <Assignment>
    <Id>125</Id>
    <CallId>9</CallId>
    <VolunteerId>231550229</VolunteerId>
    <EntryTime>2025-01-30T20:43:39</EntryTime>
    <CompletionTime>2025-01-30T20:53:39</CompletionTime>
    <CompletionStatus>Handled</CompletionStatus>
  </Assignment>
  <Assignment>
    <Id>126</Id>
    <CallId>29</CallId>
    <VolunteerId>371987611</VolunteerId>
    <EntryTime>2025-01-30T20:53:39</EntryTime>
    <CompletionTime>2025-01-30T21:03:39</CompletionTime>
    <CompletionStatus>Handled</CompletionStatus>
  </Assignment>
  <Assignment>
    <Id>127</Id>
    <CallId>7</CallId>
    <VolunteerId>282520675</VolunteerId>
    <EntryTime>2025-01-30T20:53:39</EntryTime>
    <CompletionTime>2025-01-30T21:03:39</CompletionTime>
    <CompletionStatus>Handled</CompletionStatus>
  </Assignment>
  <Assignment>
    <Id>128</Id>
    <CallId>56</CallId>
    <VolunteerId>224055293</VolunteerId>
    <EntryTime>2025-01-30T20:53:39</EntryTime>
    <CompletionTime>2025-01-30T21:03:39</CompletionTime>
    <CompletionStatus>Handled</CompletionStatus>
  </Assignment>
  <Assignment>
    <Id>129</Id>
    <CallId>17</CallId>
    <VolunteerId>265292540</VolunteerId>
    <EntryTime>2025-01-30T20:53:39</EntryTime>
    <CompletionTime>2025-01-30T21:03:39</CompletionTime>
    <CompletionStatus>Handled</CompletionStatus>
  </Assignment>
  <Assignment>
    <Id>130</Id>
    <CallId>51</CallId>
    <VolunteerId>280066259</VolunteerId>
    <EntryTime>2025-01-30T21:03:39</EntryTime>
    <CompletionTime>2025-01-30T21:13:39</CompletionTime>
    <CompletionStatus>Handled</CompletionStatus>
  </Assignment>
  <Assignment>
    <Id>131</Id>
    <CallId>18</CallId>
    <VolunteerId>232312132</VolunteerId>
    <EntryTime>2025-01-30T21:03:39</EntryTime>
    <CompletionTime>2025-01-30T21:13:39</CompletionTime>
    <CompletionStatus>Handled</CompletionStatus>
  </Assignment>
  <Assignment>
    <Id>132</Id>
    <CallId>5</CallId>
    <VolunteerId>203762463</VolunteerId>
    <EntryTime>2025-01-30T21:13:39</EntryTime>
    <CompletionTime>2025-01-30T21:23:39</CompletionTime>
    <CompletionStatus>Handled</CompletionStatus>
  </Assignment>
  <Assignment>
    <Id>133</Id>
    <CallId>1</CallId>
    <VolunteerId>280066259</VolunteerId>
    <EntryTime>2025-01-30T21:23:39</EntryTime>
    <CompletionTime>2025-01-30T21:33:39</CompletionTime>
    <CompletionStatus>Handled</CompletionStatus>
  </Assignment>
  <Assignment>
    <Id>134</Id>
    <CallId>62</CallId>
    <VolunteerId>282873264</VolunteerId>
    <EntryTime>2025-01-30T21:23:39</EntryTime>
    <CompletionTime>2025-01-30T21:33:39</CompletionTime>
    <CompletionStatus>Handled</CompletionStatus>
  </Assignment>
  <Assignment>
    <Id>135</Id>
    <CallId>15</CallId>
    <VolunteerId>282520675</VolunteerId>
    <EntryTime>2025-01-30T21:33:39</EntryTime>
    <CompletionTime>2025-01-30T21:43:39</CompletionTime>
    <CompletionStatus>Handled</CompletionStatus>
  </Assignment>
  <Assignment>
    <Id>136</Id>
    <CallId>62</CallId>
    <VolunteerId>265292540</VolunteerId>
    <EntryTime>2025-01-30T21:33:39</EntryTime>
    <CompletionTime>2025-01-30T21:43:39</CompletionTime>
    <CompletionStatus>Handled</CompletionStatus>
  </Assignment>
  <Assignment>
    <Id>137</Id>
    <CallId>20</CallId>
    <VolunteerId>388195505</VolunteerId>
    <EntryTime>2025-01-30T21:33:39</EntryTime>
    <CompletionTime>2025-01-30T21:43:39</CompletionTime>
    <CompletionStatus>Handled</CompletionStatus>
  </Assignment>
  <Assignment>
    <Id>138</Id>
    <CallId>16</CallId>
    <VolunteerId>231550229</VolunteerId>
    <EntryTime>2025-01-30T21:33:39</EntryTime>
    <CompletionTime>2025-01-30T21:43:39</CompletionTime>
    <CompletionStatus>Handled</CompletionStatus>
  </Assignment>
  <Assignment>
    <Id>139</Id>
    <CallId>59</CallId>
    <VolunteerId>328308721</VolunteerId>
    <EntryTime>2025-01-30T21:33:39</EntryTime>
    <CompletionTime>2025-01-30T21:43:39</CompletionTime>
    <CompletionStatus>Handled</CompletionStatus>
  </Assignment>
  <Assignment>
    <Id>140</Id>
    <CallId>21</CallId>
    <VolunteerId>203762463</VolunteerId>
    <EntryTime>2025-01-30T21:43:39</EntryTime>
    <CompletionTime>2025-01-30T21:53:39</CompletionTime>
    <CompletionStatus>Handled</CompletionStatus>
  </Assignment>
  <Assignment>
    <Id>141</Id>
    <CallId>55</CallId>
    <VolunteerId>282873264</VolunteerId>
    <EntryTime>2025-01-30T21:53:39</EntryTime>
    <CompletionTime>2025-01-30T22:03:39</CompletionTime>
    <CompletionStatus>Handled</CompletionStatus>
  </Assignment>
  <Assignment>
    <Id>142</Id>
    <CallId>16</CallId>
    <VolunteerId>328308721</VolunteerId>
    <EntryTime>2025-01-30T21:53:39</EntryTime>
    <CompletionTime>2025-01-30T22:03:39</CompletionTime>
    <CompletionStatus>Handled</CompletionStatus>
  </Assignment>
  <Assignment>
    <Id>143</Id>
    <CallId>28</CallId>
    <VolunteerId>282520675</VolunteerId>
    <EntryTime>2025-01-30T22:03:39</EntryTime>
    <CompletionTime>2025-01-30T22:13:39</CompletionTime>
    <CompletionStatus>Handled</CompletionStatus>
  </Assignment>
  <Assignment>
    <Id>144</Id>
    <CallId>14</CallId>
    <VolunteerId>224055293</VolunteerId>
    <EntryTime>2025-01-30T22:03:39</EntryTime>
    <CompletionTime>2025-01-30T22:13:39</CompletionTime>
    <CompletionStatus>Handled</CompletionStatus>
  </Assignment>
  <Assignment>
    <Id>145</Id>
    <CallId>51</CallId>
    <VolunteerId>280066259</VolunteerId>
    <EntryTime>2025-01-30T22:03:39</EntryTime>
    <CompletionTime>2025-01-30T22:13:39</CompletionTime>
    <CompletionStatus>Handled</CompletionStatus>
  </Assignment>
  <Assignment>
    <Id>146</Id>
    <CallId>16</CallId>
    <VolunteerId>320162951</VolunteerId>
    <EntryTime>2025-01-30T22:03:39</EntryTime>
    <CompletionTime>2025-01-30T22:13:39</CompletionTime>
    <CompletionStatus>Handled</CompletionStatus>
  </Assignment>
  <Assignment>
    <Id>147</Id>
    <CallId>44</CallId>
    <VolunteerId>202973020</VolunteerId>
    <EntryTime>2025-01-30T22:03:39</EntryTime>
    <CompletionTime>2025-01-30T22:13:39</CompletionTime>
    <CompletionStatus>Handled</CompletionStatus>
  </Assignment>
  <Assignment>
    <Id>148</Id>
    <CallId>52</CallId>
    <VolunteerId>282873264</VolunteerId>
    <EntryTime>2025-01-30T22:13:39</EntryTime>
    <CompletionTime>2025-01-30T22:23:39</CompletionTime>
    <CompletionStatus>Handled</CompletionStatus>
  </Assignment>
  <Assignment>
    <Id>149</Id>
    <CallId>11</CallId>
    <VolunteerId>265292540</VolunteerId>
    <EntryTime>2025-01-30T22:13:39</EntryTime>
    <CompletionTime>2025-01-30T22:23:39</CompletionTime>
    <CompletionStatus>Handled</CompletionStatus>
  </Assignment>
  <Assignment>
    <Id>150</Id>
    <CallId>16</CallId>
    <VolunteerId>231550229</VolunteerId>
    <EntryTime>2025-01-30T22:13:39</EntryTime>
    <CompletionTime>2025-01-30T22:23:39</CompletionTime>
    <CompletionStatus>Handled</CompletionStatus>
  </Assignment>
  <Assignment>
    <Id>151</Id>
    <CallId>51</CallId>
    <VolunteerId>280066259</VolunteerId>
    <EntryTime>2025-01-30T22:23:39</EntryTime>
    <CompletionTime>2025-01-30T22:33:39</CompletionTime>
    <CompletionStatus>Handled</CompletionStatus>
  </Assignment>
  <Assignment>
    <Id>152</Id>
    <CallId>3</CallId>
    <VolunteerId>339054173</VolunteerId>
    <EntryTime>2025-01-30T22:23:39</EntryTime>
    <CompletionTime>2025-01-30T22:33:39</CompletionTime>
    <CompletionStatus>Handled</CompletionStatus>
  </Assignment>
  <Assignment>
    <Id>153</Id>
    <CallId>38</CallId>
    <VolunteerId>328308721</VolunteerId>
    <EntryTime>2025-01-30T22:23:39</EntryTime>
    <CompletionTime>2025-01-30T22:33:39</CompletionTime>
    <CompletionStatus>Handled</CompletionStatus>
  </Assignment>
  <Assignment>
    <Id>154</Id>
    <CallId>39</CallId>
    <VolunteerId>282520675</VolunteerId>
    <EntryTime>2025-01-30T22:33:39</EntryTime>
    <CompletionTime>2025-01-30T22:43:39</CompletionTime>
    <CompletionStatus>Handled</CompletionStatus>
  </Assignment>
  <Assignment>
    <Id>155</Id>
    <CallId>32</CallId>
    <VolunteerId>224055293</VolunteerId>
    <EntryTime>2025-01-30T22:33:39</EntryTime>
    <CompletionTime>2025-01-30T22:43:39</CompletionTime>
    <CompletionStatus>Handled</CompletionStatus>
  </Assignment>
  <Assignment>
    <Id>156</Id>
    <CallId>25</CallId>
    <VolunteerId>202973020</VolunteerId>
    <EntryTime>2025-01-30T22:33:39</EntryTime>
    <CompletionTime>2025-01-30T22:43:39</CompletionTime>
    <CompletionStatus>Handled</CompletionStatus>
  </Assignment>
  <Assignment>
    <Id>157</Id>
    <CallId>18</CallId>
    <VolunteerId>232312132</VolunteerId>
    <EntryTime>2025-01-30T22:33:39</EntryTime>
    <CompletionTime>2025-01-30T22:43:39</CompletionTime>
    <CompletionStatus>Handled</CompletionStatus>
  </Assignment>
  <Assignment>
    <Id>158</Id>
    <CallId>54</CallId>
    <VolunteerId>371987611</VolunteerId>
    <EntryTime>2025-01-30T22:43:39</EntryTime>
    <CompletionTime>2025-01-30T22:53:39</CompletionTime>
    <CompletionStatus>Handled</CompletionStatus>
  </Assignment>
  <Assignment>
    <Id>159</Id>
    <CallId>16</CallId>
    <VolunteerId>231550229</VolunteerId>
    <EntryTime>2025-01-30T22:43:39</EntryTime>
    <CompletionTime>2025-01-30T22:53:39</CompletionTime>
    <CompletionStatus>Handled</CompletionStatus>
  </Assignment>
  <Assignment>
    <Id>160</Id>
    <CallId>25</CallId>
    <VolunteerId>328308721</VolunteerId>
    <EntryTime>2025-01-30T22:43:39</EntryTime>
    <CompletionTime>2025-01-30T22:53:39</CompletionTime>
    <CompletionStatus>Handled</CompletionStatus>
  </Assignment>
  <Assignment>
    <Id>161</Id>
    <CallId>10</CallId>
    <VolunteerId>282520675</VolunteerId>
    <EntryTime>2025-01-30T22:53:39</EntryTime>
    <CompletionTime>2025-01-30T23:03:39</CompletionTime>
    <CompletionStatus>Handled</CompletionStatus>
  </Assignment>
  <Assignment>
    <Id>162</Id>
    <CallId>64</CallId>
    <VolunteerId>224055293</VolunteerId>
    <EntryTime>2025-01-30T22:53:39</EntryTime>
    <CompletionTime>2025-01-30T23:03:39</CompletionTime>
    <CompletionStatus>Handled</CompletionStatus>
  </Assignment>
  <Assignment>
    <Id>163</Id>
    <CallId>56</CallId>
    <VolunteerId>320162951</VolunteerId>
    <EntryTime>2025-01-30T22:53:39</EntryTime>
    <CompletionTime>2025-01-30T23:03:39</CompletionTime>
    <CompletionStatus>Handled</CompletionStatus>
  </Assignment>
  <Assignment>
    <Id>165</Id>
    <CallId>15</CallId>
    <VolunteerId>339054173</VolunteerId>
    <EntryTime>2025-01-30T23:03:39</EntryTime>
    <CompletionTime xsi:nil="true" />
    <CompletionStatus xsi:nil="true" />
  </Assignment>
  <Assignment>
    <Id>164</Id>
    <CallId>4</CallId>
    <VolunteerId>371987611</VolunteerId>
    <EntryTime>2025-01-30T23:03:39</EntryTime>
    <CompletionTime>2025-01-30T23:13:39</CompletionTime>
    <CompletionStatus>Handled</CompletionStatus>
  </Assignment>
  <Assignment>
    <Id>166</Id>
    <CallId>9</CallId>
    <VolunteerId>231550229</VolunteerId>
    <EntryTime>2025-01-30T23:03:39</EntryTime>
    <CompletionTime>2025-01-30T23:13:39</CompletionTime>
    <CompletionStatus>Handled</CompletionStatus>
  </Assignment>
  <Assignment>
    <Id>167</Id>
    <CallId>0</CallId>
    <VolunteerId>371987611</VolunteerId>
    <EntryTime>2025-01-30T23:23:39</EntryTime>
    <CompletionTime>2025-01-30T23:33:39</CompletionTime>
    <CompletionStatus>Handled</CompletionStatus>
  </Assignment>
  <Assignment>
    <Id>168</Id>
    <CallId>39</CallId>
    <VolunteerId>282873264</VolunteerId>
    <EntryTime>2025-01-30T23:23:39</EntryTime>
    <CompletionTime>2025-01-30T23:33:39</CompletionTime>
    <CompletionStatus>Handled</CompletionStatus>
  </Assignment>
  <Assignment>
    <Id>169</Id>
    <CallId>60</CallId>
    <VolunteerId>203762463</VolunteerId>
    <EntryTime>2025-01-30T23:33:39</EntryTime>
    <CompletionTime>2025-01-30T23:43:39</CompletionTime>
    <CompletionStatus>Handled</CompletionStatus>
  </Assignment>
  <Assignment>
    <Id>174</Id>
    <CallId>54</CallId>
    <VolunteerId>371987611</VolunteerId>
    <EntryTime>2025-01-30T23:43:39</EntryTime>
    <CompletionTime xsi:nil="true" />
    <CompletionStatus xsi:nil="true" />
  </Assignment>
  <Assignment>
    <Id>175</Id>
    <CallId>37</CallId>
    <VolunteerId>282520675</VolunteerId>
    <EntryTime>2025-01-30T23:43:39</EntryTime>
    <CompletionTime xsi:nil="true" />
    <CompletionStatus xsi:nil="true" />
  </Assignment>
  <Assignment>
    <Id>170</Id>
    <CallId>9</CallId>
    <VolunteerId>224055293</VolunteerId>
    <EntryTime>2025-01-30T23:33:39</EntryTime>
    <CompletionTime>2025-01-30T23:43:39</CompletionTime>
    <CompletionStatus>Handled</CompletionStatus>
  </Assignment>
  <Assignment>
    <Id>171</Id>
    <CallId>53</CallId>
    <VolunteerId>388195505</VolunteerId>
    <EntryTime>2025-01-30T23:33:39</EntryTime>
    <CompletionTime>2025-01-30T23:43:39</CompletionTime>
    <CompletionStatus>Handled</CompletionStatus>
  </Assignment>
  <Assignment>
    <Id>176</Id>
    <CallId>44</CallId>
    <VolunteerId>202973020</VolunteerId>
    <EntryTime>2025-01-30T23:43:39</EntryTime>
    <CompletionTime xsi:nil="true" />
    <CompletionStatus xsi:nil="true" />
  </Assignment>
  <Assignment>
    <Id>172</Id>
    <CallId>9</CallId>
    <VolunteerId>231550229</VolunteerId>
    <EntryTime>2025-01-30T23:33:39</EntryTime>
    <CompletionTime>2025-01-30T23:43:39</CompletionTime>
    <CompletionStatus>Handled</CompletionStatus>
  </Assignment>
  <Assignment>
    <Id>173</Id>
    <CallId>32</CallId>
    <VolunteerId>328308721</VolunteerId>
    <EntryTime>2025-01-30T23:33:39</EntryTime>
    <CompletionTime>2025-01-30T23:43:39</CompletionTime>
    <CompletionStatus>Handled</CompletionStatus>
  </Assignment>
  <Assignment>
    <Id>42</Id>
    <CallId>16</CallId>
    <VolunteerId>231550229</VolunteerId>
    <EntryTime>2025-01-30T16:17:39</EntryTime>
    <CompletionTime>2025-01-30T16:18:39</CompletionTime>
    <CompletionStatus>SelfCancel</CompletionStatus>
  </Assignment>
  <Assignment>
    <Id>177</Id>
    <CallId>52</CallId>
    <VolunteerId>388195505</VolunteerId>
    <EntryTime>2025-01-31T03:03:39</EntryTime>
    <CompletionTime xsi:nil="true" />
    <CompletionStatus xsi:nil="true" />
  </Assignment>
  <Assignment>
    <Id>44</Id>
    <CallId>27</CallId>
    <VolunteerId>224055293</VolunteerId>
    <EntryTime>2025-01-30T16:18:39</EntryTime>
    <CompletionTime>2025-01-30T16:19:39</CompletionTime>
    <CompletionStatus>SelfCancel</CompletionStatus>
  </Assignment>
  <Assignment>
    <Id>178</Id>
    <CallId>18</CallId>
    <VolunteerId>232312132</VolunteerId>
    <EntryTime>2025-01-31T03:03:39</EntryTime>
    <CompletionTime xsi:nil="true" />
    <CompletionStatus xsi:nil="true" />
  </Assignment>
  <Assignment>
    <Id>179</Id>
    <CallId>1</CallId>
    <VolunteerId>280066259</VolunteerId>
    <EntryTime>2025-01-31T09:43:39</EntryTime>
    <CompletionTime xsi:nil="true" />
    <CompletionStatus xsi:nil="true" />
  </Assignment>
  <Assignment>
    <Id>180</Id>
    <CallId>32</CallId>
    <VolunteerId>224055293</VolunteerId>
    <EntryTime>2025-01-31T13:03:39</EntryTime>
    <CompletionTime xsi:nil="true" />
    <CompletionStatus xsi:nil="true" />
  </Assignment>
  <Assignment>
    <Id>181</Id>
    <CallId>16</CallId>
    <VolunteerId>328308721</VolunteerId>
    <EntryTime>2025-01-31T13:03:39</EntryTime>
    <CompletionTime xsi:nil="true" />
    <CompletionStatus xsi:nil="true" />
  </Assignment>
  <Assignment>
    <Id>54</Id>
    <CallId>16</CallId>
    <VolunteerId>231550229</VolunteerId>
    <EntryTime>2025-01-30T16:21:39</EntryTime>
    <CompletionTime>2025-01-30T16:22:39</CompletionTime>
    <CompletionStatus>AdminCancel</CompletionStatus>
  </Assignment>
  <Assignment>
    <Id>1</Id>
    <CallId>4</CallId>
    <VolunteerId>388195505</VolunteerId>
    <EntryTime>2025-01-30T14:59:39</EntryTime>
    <CompletionTime>2025-01-30T15:33:39</CompletionTime>
    <CompletionStatus>SelfCancel</CompletionStatus>
  </Assignment>
  <Assignment>
    <Id>182</Id>
    <CallId>7</CallId>
    <VolunteerId>265292540</VolunteerId>
    <EntryTime>2025-01-31T19:43:39</EntryTime>
    <CompletionTime xsi:nil="true" />
    <CompletionStatus xsi:nil="true" />
  </Assignment>
  <Assignment>
    <Id>37</Id>
    <CallId>51</CallId>
    <VolunteerId>280066259</VolunteerId>
    <EntryTime>2025-01-30T16:16:39</EntryTime>
    <CompletionTime>2025-01-30T16:17:39</CompletionTime>
    <CompletionStatus>AdminCancel</CompletionStatus>
  </Assignment>
  <Assignment>
    <Id>183</Id>
    <CallId>59</CallId>
    <VolunteerId>231550229</VolunteerId>
    <EntryTime>2025-01-31T19:43:39</EntryTime>
    <CompletionTime>2025-01-31T23:03:39</CompletionTime>
    <CompletionStatus>Handled</CompletionStatus>
  </Assignment>
  <Assignment>
    <Id>185</Id>
    <CallId>33</CallId>
    <VolunteerId>282873264</VolunteerId>
    <EntryTime>2025-02-01T02:23:39</EntryTime>
    <CompletionTime xsi:nil="true" />
    <CompletionStatus xsi:nil="true" />
  </Assignment>
  <Assignment>
    <Id>184</Id>
    <CallId>58</CallId>
    <VolunteerId>320162951</VolunteerId>
    <EntryTime>2025-01-31T23:03:39</EntryTime>
    <CompletionTime>2025-02-01T02:23:39</CompletionTime>
    <CompletionStatus>Handled</CompletionStatus>
  </Assignment>
  <Assignment>
    <Id>186</Id>
    <CallId>14</CallId>
    <VolunteerId>320162951</VolunteerId>
    <EntryTime>2025-02-01T05:43:39</EntryTime>
    <CompletionTime xsi:nil="true" />
    <CompletionStatus xsi:nil="true" />
  </Assignment>
  <Assignment>
    <Id>52</Id>
    <CallId>31</CallId>
    <VolunteerId>339054173</VolunteerId>
    <EntryTime>2025-01-30T16:20:39</EntryTime>
    <CompletionTime>2025-01-30T16:21:39</CompletionTime>
    <CompletionStatus>SelfCancel</CompletionStatus>
  </Assignment>
  <Assignment>
    <Id>187</Id>
    <CallId>38</CallId>
    <VolunteerId>231550229</VolunteerId>
    <EntryTime>2025-02-01T12:23:39</EntryTime>
    <CompletionTime xsi:nil="true" />
    <CompletionStatus xsi:nil="true" />
  </Assignment>
  <Assignment>
    <Id>33</Id>
    <CallId>27</CallId>
    <VolunteerId>339054173</VolunteerId>
    <EntryTime>2025-01-30T16:14:39</EntryTime>
    <CompletionTime>2025-01-30T16:15:39</CompletionTime>
    <CompletionStatus>SelfCancel</CompletionStatus>
  </Assignment>
  <Assignment>
    <Id>15</Id>
    <CallId>30</CallId>
    <VolunteerId>320162951</VolunteerId>
    <EntryTime>2025-01-30T15:05:39</EntryTime>
    <CompletionTime>2025-01-30T15:12:39</CompletionTime>
    <CompletionStatus>SelfCancel</CompletionStatus>
  </Assignment>
  <Assignment>
    <Id>38</Id>
    <CallId>18</CallId>
    <VolunteerId>232312132</VolunteerId>
    <EntryTime>2025-01-30T16:16:39</EntryTime>
    <CompletionTime>2025-01-30T16:17:39</CompletionTime>
    <CompletionStatus>SelfCancel</CompletionStatus>
  </Assignment>
</ArrayOfAssignment>